aiopenapi3/__init__.py
aiopenapi3/__main__.py
aiopenapi3/_types.py
aiopenapi3/base.py
aiopenapi3/cli.py
aiopenapi3/debug.py
aiopenapi3/errors.py
aiopenapi3/json.py
aiopenapi3/loader.py
aiopenapi3/log.py
aiopenapi3/me.py
aiopenapi3/model.py
aiopenapi3/openapi.py
aiopenapi3/plugin.py
aiopenapi3/pydanticv2.py
aiopenapi3/request.py
aiopenapi3/version.py
aiopenapi3/extra/__init__.py
aiopenapi3/extra/cookies.py
aiopenapi3/extra/reduce.py
aiopenapi3/v20/__init__.py
aiopenapi3/v20/general.py
aiopenapi3/v20/glue.py
aiopenapi3/v20/info.py
aiopenapi3/v20/parameter.py
aiopenapi3/v20/paths.py
aiopenapi3/v20/root.py
aiopenapi3/v20/schemas.py
aiopenapi3/v20/security.py
aiopenapi3/v20/tag.py
aiopenapi3/v20/xml.py
aiopenapi3/v30/__init__.py
aiopenapi3/v30/components.py
aiopenapi3/v30/example.py
aiopenapi3/v30/formdata.py
aiopenapi3/v30/general.py
aiopenapi3/v30/glue.py
aiopenapi3/v30/info.py
aiopenapi3/v30/media.py
aiopenapi3/v30/parameter.py
aiopenapi3/v30/paths.py
aiopenapi3/v30/root.py
aiopenapi3/v30/schemas.py
aiopenapi3/v30/security.py
aiopenapi3/v30/servers.py
aiopenapi3/v30/tag.py
aiopenapi3/v30/xml.py
aiopenapi3/v31/__init__.py
aiopenapi3/v31/components.py
aiopenapi3/v31/example.py
aiopenapi3/v31/general.py
aiopenapi3/v31/info.py
aiopenapi3/v31/media.py
aiopenapi3/v31/parameter.py
aiopenapi3/v31/paths.py
aiopenapi3/v31/root.py
aiopenapi3/v31/schemas.py
aiopenapi3/v31/security.py
aiopenapi3/v31/servers.py
aiopenapi3/v31/tag.py
aiopenapi3/v31/xml.py
aiopenapi3-0.8.0.dist-info/METADATA
aiopenapi3-0.8.0.dist-info/WHEEL
aiopenapi3-0.8.0.dist-info/entry_points.txt
aiopenapi3-0.8.0.dist-info/top_level.txt
aiopenapi3-0.8.0.dist-info/RECORD
