Metadata-Version: 2.2
Name: aiopenapi3
Version: 0.8.0
Summary: client and validator for OpenAPI3 3.0, OpenAPI 3.1, Swagger 2.0
Author-email: Markus Kötter <commonism@users.noreply.github.com>
License: BSD-3-Clause
Project-URL: Documentation, https://aiopenapi3.readthedocs.io/
Project-URL: Repository, https://github.com/commonism/aiopenapi3
Classifier: Development Status :: 3 - Alpha
Classifier: Environment :: Web Environment
Classifier: Framework :: AsyncIO
Classifier: Intended Audience :: Developers
Classifier: Intended Audience :: Information Technology
Classifier: Intended Audience :: System Administrators
Classifier: License :: OSI Approved :: BSD License
Classifier: Operating System :: OS Independent
Classifier: Topic :: Internet
Classifier: Topic :: Internet :: WWW/HTTP
Classifier: Topic :: Software Development
Classifier: Topic :: Software Development :: Libraries
Classifier: Topic :: Software Development :: Libraries :: Application Frameworks
Classifier: Topic :: Software Development :: Libraries :: Python Modules
Classifier: Typing :: Typed
Classifier: Programming Language :: Python :: 3
Classifier: Programming Language :: Python :: 3 :: Only
Classifier: Programming Language :: Python :: 3.9
Classifier: Programming Language :: Python :: 3.10
Classifier: Programming Language :: Python :: 3.11
Classifier: Programming Language :: Python :: 3.12
Classifier: Programming Language :: Python :: 3.13
Requires-Python: >=3.9
Requires-Dist: PyYaml
Requires-Dist: pydantic>=2.10.5
Requires-Dist: email-validator
Requires-Dist: yarl
Requires-Dist: httpx
Requires-Dist: more-itertools
Requires-Dist: typing_extensions; python_version < "3.10"
Requires-Dist: jmespath
Provides-Extra: auth
Requires-Dist: httpx-auth>=0.21.0; extra == "auth"
Provides-Extra: socks
Requires-Dist: httpx-socks; extra == "socks"
Provides-Extra: types
Requires-Dist: pydantic-extra-types>=2.10.1; extra == "types"
